pyadms-0.0.4.data/data/pyadms_data/include/constants.vams
pyadms-0.0.4.data/data/pyadms_data/include/disciplines.vams
pyadms/nstart.py
pyadms/admsJSON.py
pyadms/adms_printer.py
pyadms/admsJSON
pyadms/__init__.py
pyadms/adms_visitor.py
pyadms/adms_loader.py
pyadms/adms_expression.py
pyadms-0.0.4.dist-info/COPYING
pyadms-0.0.4.dist-info/LICENSE
pyadms-0.0.4.dist-info/top_level.txt
pyadms-0.0.4.dist-info/WHEEL
pyadms-0.0.4.dist-info/NOTICE
pyadms-0.0.4.dist-info/RECORD
pyadms-0.0.4.dist-info/METADATA
pyadms-0.0.4.dist-info/entry_points.txt
