Metadata-Version: 2.1
Name: pyadms
Version: 0.0.4
Summary: pyadms: Verilog-A Compiler
Home-page: https://github.com/pyadms/pyadms
Author: Juan Sanchez
Author-email: info@devsim.com
License: Apache License, Version 2.0, LGPL 2.1
Project-URL: Bug Tracker, https://github.com/pyadms/pyadms/issues
Project-URL: Source Code, https://github.com/pyadms/pyadms
Classifier: Development Status :: 3 - Alpha
Classifier: Intended Audience :: Science/Research
Classifier: License :: OSI Approved :: Apache Software License
Classifier: License :: OSI Approved :: GNU Lesser General Public License v2 (LGPLv2)
Classifier: Programming Language :: Python :: 3
Classifier: Programming Language :: C++
Classifier: Topic :: Scientific/Engineering :: Electronic Design Automation (EDA)
License-File: LICENSE
License-File: COPYING
License-File: NOTICE
